vacsol_ml/__init__.py
vacsol_ml/cli.py
vacsol_ml/Data/iFeature/README.md
vacsol_ml/Data/iFeature/cluster.py
vacsol_ml/Data/iFeature/feaSelector.py
vacsol_ml/Data/iFeature/iFeature.py
vacsol_ml/Data/iFeature/iFeatureManual.pdf
vacsol_ml/Data/iFeature/iFeaturePseKRAAC.py
vacsol_ml/Data/iFeature/ifeature1.tsv
vacsol_ml/Data/iFeature/input.fasta
vacsol_ml/Data/iFeature/PseKRAAC/__init__.py
vacsol_ml/Data/iFeature/PseKRAAC/type1.py
vacsol_ml/Data/iFeature/PseKRAAC/type10.py
vacsol_ml/Data/iFeature/PseKRAAC/type11.py
vacsol_ml/Data/iFeature/PseKRAAC/type12.py
vacsol_ml/Data/iFeature/PseKRAAC/type13.py
vacsol_ml/Data/iFeature/PseKRAAC/type14.py
vacsol_ml/Data/iFeature/PseKRAAC/type15.py
vacsol_ml/Data/iFeature/PseKRAAC/type16.py
vacsol_ml/Data/iFeature/PseKRAAC/type2.py
vacsol_ml/Data/iFeature/PseKRAAC/type3A.py
vacsol_ml/Data/iFeature/PseKRAAC/type3B.py
vacsol_ml/Data/iFeature/PseKRAAC/type4.py
vacsol_ml/Data/iFeature/PseKRAAC/type5.py
vacsol_ml/Data/iFeature/PseKRAAC/type6A.py
vacsol_ml/Data/iFeature/PseKRAAC/type6B.py
vacsol_ml/Data/iFeature/PseKRAAC/type6C.py
vacsol_ml/Data/iFeature/PseKRAAC/type7.py
vacsol_ml/Data/iFeature/PseKRAAC/type8.py
vacsol_ml/Data/iFeature/PseKRAAC/type9.py
vacsol_ml/Data/iFeature/clusters/__init__.py
vacsol_ml/Data/iFeature/clusters/apc.py
vacsol_ml/Data/iFeature/clusters/dbscan.py
vacsol_ml/Data/iFeature/clusters/hcluster.py
vacsol_ml/Data/iFeature/clusters/kmeans.py
vacsol_ml/Data/iFeature/clusters/meanshift.py
vacsol_ml/Data/iFeature/clusters/pca.py
vacsol_ml/Data/iFeature/clusters/readCode.py
vacsol_ml/Data/iFeature/clusters/saveCluster.py
vacsol_ml/Data/iFeature/clusters/tsne.py
vacsol_ml/Data/iFeature/codes/AAC.py
vacsol_ml/Data/iFeature/codes/AAINDEX.py
vacsol_ml/Data/iFeature/codes/APAAC.py
vacsol_ml/Data/iFeature/codes/ASA.py
vacsol_ml/Data/iFeature/codes/BINARY.py
vacsol_ml/Data/iFeature/codes/BLOSUM62.py
vacsol_ml/Data/iFeature/codes/CKSAAGP.py
vacsol_ml/Data/iFeature/codes/CKSAAP.py
vacsol_ml/Data/iFeature/codes/CTDC.py
vacsol_ml-1.0.5.dist-info/METADATA
vacsol_ml-1.0.5.dist-info/WHEEL
vacsol_ml-1.0.5.dist-info/entry_points.txt
vacsol_ml-1.0.5.dist-info/top_level.txt
vacsol_ml-1.0.5.dist-info/RECORD
