Metadata-Version: 2.4
Name: vacsol-ml
Version: 1.0.5
Summary: VacSol-ML (ESKAPE): ML-driven vaccine target discovery targeting ESKAPE pathogens
Requires-Python: <3.13,>=3.10
Requires-Dist: Django==5.2.10
Requires-Dist: django-mathfilters==1.0.0
Requires-Dist: iedb==0.0.2
Requires-Dist: joblib==1.5.3
Requires-Dist: numpy==2.2.6
Requires-Dist: pandas==2.3.3
Requires-Dist: pybiolib==1.2.1768
Requires-Dist: scikit-learn==1.4.2
Requires-Dist: tensorflow==2.20.0
Requires-Dist: keras==3.12.0
Requires-Dist: bio==1.8.1
